{
  "doc": "math_p24",
  "sha256": "654d3c16",
  "pages": 22,
  "pdf": "/papers/SimultaneousSuper-resolutionandDepthEstimationforSatelliteImagesBasedonDiffusionModel.pdf",
  "generated": "2025-10-02T08:39:21.417Z",
  "pk": {
    "doc": "math_p24",
    "sha256": "654d3c16",
    "pages": 22
  },
  "rasters": [
    "math/math_p24/math_p24.page01.png",
    "math/math_p24/math_p24.page02.png",
    "math/math_p24/math_p24.page03.png",
    "math/math_p24/math_p24.page04.png",
    "math/math_p24/math_p24.page05.png",
    "math/math_p24/math_p24.page06.png",
    "math/math_p24/math_p24.page07.png",
    "math/math_p24/math_p24.page08.png",
    "math/math_p24/math_p24.page09.png",
    "math/math_p24/math_p24.page10.png",
    "math/math_p24/math_p24.page11.png",
    "math/math_p24/math_p24.page12.png",
    "math/math_p24/math_p24.page13.png",
    "math/math_p24/math_p24.page14.png",
    "math/math_p24/math_p24.page15.png",
    "math/math_p24/math_p24.page16.png",
    "math/math_p24/math_p24.page17.png",
    "math/math_p24/math_p24.page18.png",
    "math/math_p24/math_p24.page19.png",
    "math/math_p24/math_p24.page20.png",
    "math/math_p24/math_p24.page21.png",
    "math/math_p24/math_p24.page22.png"
  ],
  "ocr": []
}
